{"nm":"Main Scene","ddd":0,"h":300,"w":300,"meta":{"g":"@lottiefiles/creator 1.29.0"},"layers":[{"ty":4,"nm":"4 (In/Out)","sr":1,"st":0,"op":201,"ip":0,"hd":false,"ddd":0,"bm":0,"hasMask":false,"ao":0,"ks":{"a":{"a":0,"k":[0,0]},"s":{"a":0,"k":[100,100]},"sk":{"a":0,"k":0},"p":{"a":0,"k":[0,0]},"r":{"a":0,"k":0},"sa":{"a":0,"k":0},"o":{"a":1,"k":[{"h":1,"o":{"x":0.167,"y":0.167},"i":{"x":0.833,"y":0.833},"s":[0],"t":0},{"s":[100],"t":57}]}},"shapes":[{"ty":"gr","bm":0,"hd":false,"nm":"4","it":[{"ty":"sh","bm":0,"hd":false,"nm":"Path 23","d":1,"ks":{"a":0,"k":{"c":false,"i":[[0,0],[-22.5,-7.5],[0,0]],"o":[[0,0],[22.5,7.5],[0,0]],"v":[[61,78.5],[78,100.5],[94,115.5]]}}},{"ty":"st","bm":0,"hd":false,"nm":"Stroke","lc":2,"lj":1,"ml":4,"o":{"a":0,"k":100},"w":{"a":0,"k":5},"c":{"a":0,"k":[0.1294,0.3882,0.3255]}},{"ty":"tm","bm":0,"hd":false,"nm":"Trim","e":{"a":1,"k":[{"o":{"x":0.333,"y":0},"i":{"x":0.667,"y":1},"s":[0],"t":57},{"s":[100],"t":154}]},"o":{"a":0,"k":0},"s":{"a":1,"k":[{"o":{"x":0.333,"y":0},"i":{"x":0.667,"y":1},"s":[0],"t":94},{"s":[100],"t":170}]},"m":1},{"ty":"tr","a":{"a":0,"k":[77.63932366313759,97]},"s":{"a":0,"k":[100,100]},"sk":{"a":0,"k":0},"p":{"a":0,"k":[228.6393127441406,248]},"r":{"a":0,"k":0},"sa":{"a":0,"k":0},"o":{"a":0,"k":100}}]}],"ind":1},{"ty":4,"nm":"3 (In/Out)","sr":1,"st":0,"op":201,"ip":0,"hd":false,"ddd":0,"bm":0,"hasMask":false,"ao":0,"ks":{"a":{"a":0,"k":[0,0]},"s":{"a":0,"k":[100,100]},"sk":{"a":0,"k":0},"p":{"a":0,"k":[0,0]},"r":{"a":0,"k":0},"sa":{"a":0,"k":0},"o":{"a":1,"k":[{"h":1,"o":{"x":0.167,"y":0.167},"i":{"x":0.833,"y":0.833},"s":[0],"t":0},{"s":[100],"t":57}]}},"shapes":[{"ty":"gr","bm":0,"hd":false,"nm":"3","it":[{"ty":"sh","bm":0,"hd":false,"nm":"Path 24","d":1,"ks":{"a":0,"k":{"c":false,"i":[[0,0],[29.459,25.084],[5,-25.75],[5.75,-0.75]],"o":[[0,0],[-25.25,-21.5],[-5.515000000000001,28.405],[0,0]],"v":[[-75,68.75],[-107.25,86.5],[-94,84],[-128.75,113]]}}},{"ty":"st","bm":0,"hd":false,"nm":"Stroke","lc":2,"lj":1,"ml":4,"o":{"a":0,"k":100},"w":{"a":0,"k":5},"c":{"a":0,"k":[0.2196,1,0.8157]}},{"ty":"tm","bm":0,"hd":false,"nm":"Trim","e":{"a":1,"k":[{"o":{"x":0.333,"y":0},"i":{"x":0.667,"y":1},"s":[0],"t":57},{"s":[100],"t":154}]},"o":{"a":0,"k":0},"s":{"a":1,"k":[{"o":{"x":0.333,"y":0},"i":{"x":0.667,"y":1},"s":[0],"t":94},{"s":[100],"t":170}]},"m":1},{"ty":"tr","a":{"a":0,"k":[-101.875,90.18175430500833]},"s":{"a":0,"k":[91.45600387352259,89.38100198887986]},"sk":{"a":0,"k":-0.000001571805555928342},"p":{"a":0,"k":[249.8425903320312,58.3128547668457]},"r":{"a":0,"k":-157.0000003290917},"sa":{"a":0,"k":0},"o":{"a":0,"k":100}}]}],"ind":2},{"ty":4,"nm":"2 (In/Out)","sr":1,"st":0,"op":201,"ip":0,"hd":false,"ddd":0,"bm":0,"hasMask":false,"ao":0,"ks":{"a":{"a":0,"k":[0,0]},"s":{"a":0,"k":[100,100]},"sk":{"a":0,"k":0},"p":{"a":0,"k":[0,0]},"r":{"a":0,"k":0},"sa":{"a":0,"k":0},"o":{"a":1,"k":[{"h":1,"o":{"x":0.167,"y":0.167},"i":{"x":0.833,"y":0.833},"s":[0],"t":0},{"s":[100],"t":57}]}},"shapes":[{"ty":"gr","bm":0,"hd":false,"nm":"2","it":[{"ty":"sh","bm":0,"hd":false,"nm":"Path 25","d":1,"ks":{"a":0,"k":{"c":false,"i":[[0,0],[20.5,4.5],[0,0],[18.25,9.25],[3.5,-3.25]],"o":[[0,0],[-20.5,-4.5],[0,0],[-18.25,-9.25],[0,0]],"v":[[90.75,-122.25],[83.5,-110.5],[81.25,-97.25],[69.75,-93.25],[61,-75.75]]}}},{"ty":"st","bm":0,"hd":false,"nm":"Stroke","lc":2,"lj":1,"ml":4,"o":{"a":0,"k":100},"w":{"a":0,"k":5},"c":{"a":0,"k":[0.6392,1,0.9137]}},{"ty":"tm","bm":0,"hd":false,"nm":"Trim","e":{"a":1,"k":[{"o":{"x":0.333,"y":0},"i":{"x":0.667,"y":1},"s":[0],"t":57},{"s":[100],"t":154}]},"o":{"a":0,"k":0},"s":{"a":1,"k":[{"o":{"x":0.333,"y":0},"i":{"x":0.667,"y":1},"s":[0],"t":94},{"s":[100],"t":170}]},"m":1},{"ty":"tr","a":{"a":0,"k":[77.3523450439922,-99]},"s":{"a":0,"k":[100,100]},"sk":{"a":0,"k":0},"p":{"a":0,"k":[56.35234832763672,248]},"r":{"a":0,"k":0},"sa":{"a":0,"k":0},"o":{"a":0,"k":100}}]}],"ind":3},{"ty":4,"nm":"1 (In/Out)","sr":1,"st":0,"op":201,"ip":0,"hd":false,"ddd":0,"bm":0,"hasMask":false,"ao":0,"ks":{"a":{"a":0,"k":[0,0]},"s":{"a":0,"k":[100,100]},"sk":{"a":0,"k":0},"p":{"a":0,"k":[0,0]},"r":{"a":0,"k":0},"sa":{"a":0,"k":0},"o":{"a":1,"k":[{"h":1,"o":{"x":0.167,"y":0.167},"i":{"x":0.833,"y":0.833},"s":[0],"t":0},{"s":[100],"t":57}]}},"shapes":[{"ty":"gr","bm":0,"hd":false,"nm":"1","it":[{"ty":"sh","bm":0,"hd":false,"nm":"Path 26","d":1,"ks":{"a":0,"k":{"c":false,"i":[[0,0],[33.75,1]],"o":[[0,0],[0,0]],"v":[[-57.75,-75.75],[-90.75,-107.5]]}}},{"ty":"st","bm":0,"hd":false,"nm":"Stroke","lc":2,"lj":1,"ml":4,"o":{"a":0,"k":100},"w":{"a":0,"k":5},"c":{"a":0,"k":[0.4392,1,0.8667]}},{"ty":"tm","bm":0,"hd":false,"nm":"Trim","e":{"a":1,"k":[{"o":{"x":0.333,"y":0},"i":{"x":0.667,"y":1},"s":[0],"t":57},{"s":[100],"t":154}]},"o":{"a":0,"k":0},"s":{"a":1,"k":[{"o":{"x":0.333,"y":0},"i":{"x":0.667,"y":1},"s":[0],"t":94},{"s":[100],"t":170}]},"m":1},{"ty":"tr","a":{"a":0,"k":[-74.24932095971027,-91.625]},"s":{"a":0,"k":[109.7560048103333,101.856005191803]},"sk":{"a":0,"k":0},"p":{"a":0,"k":[63.86056518554688,52.41979598999023]},"r":{"a":0,"k":0},"sa":{"a":0,"k":0},"o":{"a":0,"k":100}}]}],"ind":4},{"ty":4,"nm":"checkmark/success Outlines","sr":1,"st":0,"op":201,"ip":0,"hd":false,"ddd":0,"bm":0,"hasMask":false,"ao":0,"ks":{"a":{"a":0,"k":[99,99]},"s":{"a":1,"k":[{"o":{"x":0.333,"y":0},"i":{"x":0.667,"y":1},"s":[100,100],"t":0},{"o":{"x":0.333,"y":0},"i":{"x":0.667,"y":1},"s":[27,27],"t":40},{"s":[100,100],"t":70}]},"sk":{"a":0,"k":0},"p":{"a":0,"k":[150.06,150.061]},"r":{"a":0,"k":0},"sa":{"a":0,"k":0},"o":{"a":0,"k":100}},"shapes":[{"ty":"gr","bm":0,"hd":false,"nm":"Group 1","it":[{"ty":"sh","bm":0,"hd":false,"nm":"Path 27","d":1,"ks":{"a":0,"k":{"c":true,"i":[[0,0],[0.8309999999999995,1.408999999999999],[0,0],[-0.6219999999999999,2.0040000000000013],[-1.8440000000000012,1.0429999999999993],[-2.082999999999998,-0.4740000000000002],[-1.215000000000003,-1.739999999999998],[0,0],[-0.9490000000000016,0.5370000000000008],[0,0],[-2.040999999999997,-0.6320000000000014],[-1.075000000000003,-1.8260000000000005],[0.46300000000000097,-2.0470000000000006],[1.756,-1.181000000000001],[0,0]],"o":[[-1.4239999999999995,0.8049999999999997],[0,0],[-0.9299999999999997,-1.899000000000001],[0.6219999999999999,-2.006],[1.8440000000000012,-1.042000000000002],[2.084000000000003,0.4740000000000002],[0,0],[0.5530000000000008,0.9390000000000001],[0,0],[1.9209999999999994,-0.8990000000000009],[2.042000000000002,0.6310000000000002],[1.0760000000000005,1.823],[-0.46300000000000097,2.0470000000000006],[0,0],[0,0]],"v":[[-26.138,30.587],[-30.199,29.498],[-58.899,-19.189],[-59.378,-25.261],[-55.542,-30.001],[-49.433,-30.884],[-44.302,-27.441],[-23.618,7.647],[-20.911,8.371],[47.571,-30.344],[53.736,-30.76],[58.584,-26.94],[59.537,-20.918],[56.086,-15.898],[-26.138,30.587]]}}},{"ty":"fl","bm":0,"hd":false,"nm":"Fill","c":{"a":0,"k":[1,1,1]},"r":1,"o":{"a":0,"k":100}},{"ty":"tr","a":{"a":0,"k":[0,0]},"s":{"a":0,"k":[83.631,83.631]},"sk":{"a":0,"k":0},"p":{"a":0,"k":[99.943,103.024]},"r":{"a":0,"k":-12.6},"sa":{"a":0,"k":0},"o":{"a":0,"k":100}}]},{"ty":"gr","bm":0,"hd":false,"nm":"Group 2","it":[{"ty":"sh","bm":0,"hd":false,"nm":"Path 28","d":1,"ks":{"a":0,"k":{"c":true,"i":[[0,0],[12.721,-47.478],[47.478,12.721999999999994],[-12.723,47.478],[-47.479,-12.721999999999994]],"o":[[47.479,12.721999999999994],[-12.723,47.479],[-47.47800000000001,-12.723],[12.721,-47.479],[0,0]],"v":[[23.036,-85.967],[85.969,23.035],[-23.035,85.967],[-85.966,-23.035],[23.036,-85.967]]}}},{"ty":"fl","bm":0,"hd":false,"nm":"Fill","c":{"a":1,"k":[{"o":{"x":0.167,"y":0.167},"i":{"x":0.833,"y":0.833},"s":[0.898,0.898,0.898],"t":0},{"o":{"x":0.167,"y":0.167},"i":{"x":0.833,"y":0.833},"s":[0.898,0.898,0.898],"t":33},{"s":[0.5137,0.8157,0.7451],"t":97}]},"r":1,"o":{"a":0,"k":100}},{"ty":"tr","a":{"a":0,"k":[0,0]},"s":{"a":0,"k":[100,100]},"sk":{"a":0,"k":0},"p":{"a":0,"k":[98.939,98.939]},"r":{"a":0,"k":0},"sa":{"a":0,"k":0},"o":{"a":0,"k":100}}]}],"ind":5},{"ty":4,"nm":"large-circles/success Outlines (In/Out)","sr":1,"st":0,"op":201,"ip":0,"hd":false,"ddd":0,"bm":0,"hasMask":false,"ao":0,"ks":{"a":{"a":0,"k":[0,0]},"s":{"a":0,"k":[100,100]},"sk":{"a":0,"k":0},"p":{"a":0,"k":[0,0]},"r":{"a":0,"k":0},"sa":{"a":0,"k":0},"o":{"a":1,"k":[{"h":1,"o":{"x":0.167,"y":0.167},"i":{"x":0.833,"y":0.833},"s":[0],"t":0},{"s":[100],"t":57}]}},"shapes":[{"ty":"gr","bm":0,"hd":false,"nm":"large-circles/success Outlines","it":[{"ty":"gr","bm":0,"hd":false,"nm":"Group 1","it":[{"ty":"sh","bm":0,"hd":false,"nm":"Path 29","d":1,"ks":{"a":0,"k":{"c":true,"i":[[0,0],[-1.337,-6.209],[6.209,-1.337],[1.3379999999999992,6.209],[-6.209,1.3379999999999992]],"o":[[6.208,-1.337],[1.338000000000001,6.209],[-6.209,1.338000000000001],[-1.337,-6.209],[0,0]],"v":[[-2.421,-11.243],[11.242,-2.422],[2.421,11.241],[-11.243,2.421],[-2.421,-11.243]]}}},{"ty":"fl","bm":0,"hd":false,"nm":"Fill","c":{"a":0,"k":[0.6392,1,0.9137]},"r":1,"o":{"a":0,"k":100}},{"ty":"tr","a":{"a":0,"k":[0,0]},"s":{"a":0,"k":[71,71]},"sk":{"a":0,"k":0},"p":{"a":0,"k":[173.998,145.423]},"r":{"a":0,"k":0},"sa":{"a":0,"k":0},"o":{"a":0,"k":100}}]},{"ty":"gr","bm":0,"hd":false,"nm":"Group 2","it":[{"ty":"sh","bm":0,"hd":false,"nm":"Path 30","d":1,"ks":{"a":0,"k":{"c":true,"i":[[0,0],[-1.338000000000001,-6.209],[6.209,-1.338000000000001],[1.3379999999999992,6.209],[-6.209,1.337]],"o":[[6.209,-1.338000000000001],[1.337,6.209],[-6.209,1.337],[-1.337,-6.208],[0,0]],"v":[[-2.421,-11.242],[11.242,-2.422],[2.422,11.242],[-11.243,2.422],[-2.421,-11.242]]}}},{"ty":"fl","bm":0,"hd":false,"nm":"Fill","c":{"a":0,"k":[0.0863,0.8078,0.6392]},"r":1,"o":{"a":0,"k":100}},{"ty":"tr","a":{"a":0,"k":[0,0]},"s":{"a":0,"k":[70,70]},"sk":{"a":0,"k":0},"p":{"a":0,"k":[63.997,183.011]},"r":{"a":0,"k":0},"sa":{"a":0,"k":0},"o":{"a":0,"k":100}}]},{"ty":"gr","bm":0,"hd":false,"nm":"Group 3","it":[{"ty":"sh","bm":0,"hd":false,"nm":"Path 31","d":1,"ks":{"a":0,"k":{"c":true,"i":[[0,0],[-1.337,-6.208],[6.209,-1.337],[1.3379999999999992,6.209],[-6.209,1.337]],"o":[[6.209,-1.337],[1.338000000000001,6.209],[-6.209,1.338000000000001],[-1.337,-6.209],[0,0]],"v":[[-2.421,-11.243],[11.242,-2.423],[2.421,11.242],[-11.243,2.421],[-2.421,-11.243]]}}},{"ty":"fl","bm":0,"hd":false,"nm":"Fill","c":{"a":0,"k":[0.2196,1,0.8157]},"r":1,"o":{"a":0,"k":100}},{"ty":"tr","a":{"a":0,"k":[0,0]},"s":{"a":0,"k":[70,70]},"sk":{"a":0,"k":0},"p":{"a":0,"k":[103.291,12.83]},"r":{"a":0,"k":0},"sa":{"a":0,"k":0},"o":{"a":0,"k":100}}]},{"ty":"gr","bm":0,"hd":false,"nm":"Group 4","it":[{"ty":"sh","bm":0,"hd":false,"nm":"Path 32","d":1,"ks":{"a":0,"k":{"c":true,"i":[[0,0],[-1.337,-6.209],[6.209,-1.338000000000001],[1.3379999999999992,6.209],[-6.208,1.337]],"o":[[6.209,-1.337],[1.338000000000001,6.209],[-6.209,1.337],[-1.337,-6.209],[0,0]],"v":[[-2.423,-11.242],[11.241,-2.422],[2.421,11.242],[-11.243,2.422],[-2.423,-11.242]]}}},{"ty":"fl","bm":0,"hd":false,"nm":"Fill","c":{"a":0,"k":[0.0863,0.8078,0.6392]},"r":1,"o":{"a":0,"k":100}},{"ty":"tr","a":{"a":0,"k":[0,0]},"s":{"a":0,"k":[67,67]},"sk":{"a":0,"k":0},"p":{"a":0,"k":[178.004,59.795]},"r":{"a":0,"k":0},"sa":{"a":0,"k":0},"o":{"a":0,"k":100}}]},{"ty":"gr","bm":0,"hd":false,"nm":"Group 5","it":[{"ty":"sh","bm":0,"hd":false,"nm":"Path 33","d":1,"ks":{"a":0,"k":{"c":true,"i":[[0,0],[-1.3379999999999992,-6.208],[6.209,-1.337],[1.3379999999999992,6.209],[-6.209,1.337]],"o":[[6.209,-1.337],[1.337,6.209],[-6.209,1.338000000000001],[-1.337,-6.209],[0,0]],"v":[[-2.421,-11.243],[11.243,-2.423],[2.422,11.242],[-11.243,2.421],[-2.421,-11.243]]}}},{"ty":"fl","bm":0,"hd":false,"nm":"Fill","c":{"a":0,"k":[0.4392,1,0.8667]},"r":1,"o":{"a":0,"k":100}},{"ty":"tr","a":{"a":0,"k":[0,0]},"s":{"a":0,"k":[68,68]},"sk":{"a":0,"k":0},"p":{"a":0,"k":[12.829,84.352]},"r":{"a":0,"k":0},"sa":{"a":0,"k":0},"o":{"a":0,"k":100}}]},{"ty":"tr","a":{"a":0,"k":[95.5,98]},"s":{"a":1,"k":[{"o":{"x":0.009,"y":1.621},"i":{"x":0.667,"y":1},"s":[62,62],"t":57},{"s":[124,124],"t":167}]},"sk":{"a":0,"k":0},"p":{"a":0,"k":[148,146]},"r":{"a":0,"k":0},"sa":{"a":0,"k":0},"o":{"a":1,"k":[{"o":{"x":0.167,"y":0.167},"i":{"x":0.833,"y":0.833},"s":[100],"t":140},{"s":[2],"t":173}]}}]}],"ind":6},{"ty":4,"nm":"checkmark/success Outlines (In/Out)","sr":1,"st":0,"op":201,"ip":0,"hd":false,"ddd":0,"bm":0,"hasMask":false,"ao":0,"ks":{"a":{"a":0,"k":[0,0]},"s":{"a":0,"k":[100,100]},"sk":{"a":0,"k":0},"p":{"a":0,"k":[0,0]},"r":{"a":0,"k":0},"sa":{"a":0,"k":0},"o":{"a":1,"k":[{"h":1,"o":{"x":0.167,"y":0.167},"i":{"x":0.833,"y":0.833},"s":[0],"t":0},{"s":[100],"t":167}]}},"shapes":[{"ty":"gr","bm":0,"hd":false,"nm":"checkmark/success Outlines","it":[{"ty":"gr","bm":0,"hd":false,"nm":"Group 1","it":[{"ty":"sh","bm":0,"hd":false,"nm":"Path 34","d":1,"ks":{"a":0,"k":{"c":true,"i":[[0,0],[0.8309999999999995,1.408999999999999],[0,0],[-0.6219999999999999,2.0040000000000013],[-1.8440000000000012,1.0429999999999993],[-2.082999999999998,-0.4740000000000002],[-1.215000000000003,-1.739999999999998],[0,0],[-0.9490000000000016,0.5370000000000008],[0,0],[-2.040999999999997,-0.6320000000000014],[-1.075000000000003,-1.8260000000000005],[0.46300000000000097,-2.0470000000000006],[1.756,-1.181000000000001],[0,0]],"o":[[-1.4239999999999995,0.8049999999999997],[0,0],[-0.9299999999999997,-1.899000000000001],[0.6219999999999999,-2.006],[1.8440000000000012,-1.042000000000002],[2.084000000000003,0.4740000000000002],[0,0],[0.5530000000000008,0.9390000000000001],[0,0],[1.9209999999999994,-0.8990000000000009],[2.042000000000002,0.6310000000000002],[1.0760000000000005,1.823],[-0.46300000000000097,2.0470000000000006],[0,0],[0,0]],"v":[[-26.138,30.587],[-30.199,29.498],[-58.899,-19.189],[-59.378,-25.261],[-55.542,-30.001],[-49.433,-30.884],[-44.302,-27.441],[-23.618,7.647],[-20.911,8.371],[47.571,-30.344],[53.736,-30.76],[58.584,-26.94],[59.537,-20.918],[56.086,-15.898],[-26.138,30.587]]}}},{"ty":"fl","bm":0,"hd":false,"nm":"Fill","c":{"a":0,"k":[1,1,1]},"r":1,"o":{"a":0,"k":100}},{"ty":"tr","a":{"a":0,"k":[0,0]},"s":{"a":0,"k":[100,100]},"sk":{"a":0,"k":0},"p":{"a":0,"k":[98.943,102.024]},"r":{"a":0,"k":0},"sa":{"a":0,"k":0},"o":{"a":0,"k":100}}]},{"ty":"gr","bm":0,"hd":false,"nm":"Group 2","it":[{"ty":"sh","bm":0,"hd":false,"nm":"Path 35","d":1,"ks":{"a":0,"k":{"c":true,"i":[[0,0],[12.721,-47.478],[47.478,12.721999999999994],[-12.723,47.478],[-47.479,-12.721999999999994]],"o":[[47.479,12.721999999999994],[-12.723,47.479],[-47.47800000000001,-12.723],[12.721,-47.479],[0,0]],"v":[[23.036,-85.967],[85.969,23.035],[-23.035,85.967],[-85.966,-23.035],[23.036,-85.967]]}}},{"ty":"fl","bm":0,"hd":false,"nm":"Fill","c":{"a":0,"k":[0.1882,0.7647,0.6314]},"r":1,"o":{"a":0,"k":100}},{"ty":"tr","a":{"a":0,"k":[0,0]},"s":{"a":0,"k":[100,100]},"sk":{"a":0,"k":0},"p":{"a":0,"k":[98.939,98.939]},"r":{"a":0,"k":0},"sa":{"a":0,"k":0},"o":{"a":0,"k":100}}]},{"ty":"tr","a":{"a":0,"k":[99,99]},"s":{"a":1,"k":[{"o":{"x":0.915,"y":0.651},"i":{"x":0.203,"y":0.507},"s":[93.357,93.357],"t":167},{"s":[121.357,121.357],"t":197}]},"sk":{"a":0,"k":0},"p":{"a":0,"k":[150.073,150.073]},"r":{"a":0,"k":0},"sa":{"a":0,"k":0},"o":{"a":0,"k":100}}]}],"ind":7}],"v":"5.7.0","fr":100,"op":200,"ip":0,"assets":[]}